{
    "flog": false,
    "offColors": false,
    "autoBuy": false,
    "autoBuyItems": ["cursor"],
    "smartBuy": false,
    "waitForBoost": true,
    "numberOfTries": 3,
    "limitCPS": 50000,
    "autobeep": false,
    "hidejunk": false,
    "tforce": false,
    "transferTo": false,
    "transferCoins": 30000,
    "transferPercent": 0,
    "transferInterval": 3600,
    "saveIFrameURL": true,
    "authAppType": "android",
    "checkUpdates": true,
    "updatesInterval": 300,
    "autoUpdate": true,
    "updateOnce": false
}
